cryptidy/__init__.py
cryptidy/aes_encryption.py
cryptidy/asymmetric_encryption.py
cryptidy/hf_handling.py
cryptidy/padding.py
cryptidy/symmetric_encryption.py
cryptidy-1.2.4.dist-info/LICENSE
cryptidy-1.2.4.dist-info/METADATA
cryptidy-1.2.4.dist-info/WHEEL
cryptidy-1.2.4.dist-info/top_level.txt
cryptidy-1.2.4.dist-info/RECORD
